alembic_autogenerate_enums/__init__.py
alembic_autogenerate_enums-0.1.2.dist-info/LICENSE
alembic_autogenerate_enums-0.1.2.dist-info/WHEEL
alembic_autogenerate_enums-0.1.2.dist-info/METADATA
alembic_autogenerate_enums-0.1.2.dist-info/RECORD
