Metadata-Version: 2.1
Name: alembic-autogenerate-enums
Version: 0.1.2
Summary: Alembic hook that allows enums values to be upgraded and downgraded in migrations automatically
License: MIT
Author: David Wilson
Author-email: dw@botanicus.net
Requires-Python: >=3.7,<4.0
Classifier: License :: OSI Approved :: MIT License
Classifier: Programming Language :: Python :: 3
Classifier: Programming Language :: Python :: 3.7
Classifier: Programming Language :: Python :: 3.8
Classifier: Programming Language :: Python :: 3.9
Classifier: Programming Language :: Python :: 3.10
